trytond/modules/cashbook_bookcategory/README.rst
trytond/modules/cashbook_bookcategory/__init__.py
trytond/modules/cashbook_bookcategory/book.py
trytond/modules/cashbook_bookcategory/book.xml
trytond/modules/cashbook_bookcategory/category.py
trytond/modules/cashbook_bookcategory/category.xml
trytond/modules/cashbook_bookcategory/ir.py
trytond/modules/cashbook_bookcategory/menu.xml
trytond/modules/cashbook_bookcategory/tryton.cfg
trytond/modules/cashbook_bookcategory/versiondep.txt
trytond/modules/cashbook_bookcategory/locale/de.po
trytond/modules/cashbook_bookcategory/locale/en.po
trytond/modules/cashbook_bookcategory/tests/__init__.py
trytond/modules/cashbook_bookcategory/tests/test_category.py
trytond/modules/cashbook_bookcategory/view/book_form.xml
trytond/modules/cashbook_bookcategory/view/category_form.xml
trytond/modules/cashbook_bookcategory/view/category_list.xml
trytond/modules/cashbook_bookcategory/view/category_tree.xml
mds_cashbook_bookcategory-7.0.6.dist-info/METADATA
mds_cashbook_bookcategory-7.0.6.dist-info/WHEEL
mds_cashbook_bookcategory-7.0.6.dist-info/entry_points.txt
mds_cashbook_bookcategory-7.0.6.dist-info/top_level.txt
mds_cashbook_bookcategory-7.0.6.dist-info/RECORD
